MANIFEST.in
README
__init__.py
__pkginfo__.py
ccplugin.py
schema.py
setup.py
site_cubicweb.py
cubicweb_pyramid.egg-info/PKG-INFO
cubicweb_pyramid.egg-info/SOURCES.txt
cubicweb_pyramid.egg-info/dependency_links.txt
cubicweb_pyramid.egg-info/not-zip-safe
cubicweb_pyramid.egg-info/requires.txt
cubicweb_pyramid.egg-info/top_level.txt