Metadata-Version: 1.1
Name: cubicweb-pyramid
Version: 0.2.0
Summary: Add the 'pyramid' command to cubicweb-ctl
Home-page: http://www.cubicweb.org/project/cubicweb-pyramid
Author: UNLISH S.A.S. (Montpellier, FRANCE)
Author-email: contact@unlish.com
License: LGPL
Platform: UNKNOWN
Classifier: Environment :: Web Environment
Classifier: Framework :: CubicWeb
Classifier: Programming Language :: Python
Classifier: Programming Language :: JavaScript
